k8sllm/__init__.py
k8sllm/cli.py
k8sllm/config.py
k8sllm/context_manager.py
k8sllm/k8s_executor.py
k8sllm/llm_processor.py
k8sllm-0.1.0.dist-info/METADATA
k8sllm-0.1.0.dist-info/WHEEL
k8sllm-0.1.0.dist-info/entry_points.txt
k8sllm-0.1.0.dist-info/top_level.txt
k8sllm-0.1.0.dist-info/RECORD
