Metadata-Version: 2.1
Name: k8sllm
Version: 0.1.0
Summary: A natural language interface for Kubernetes operations
Home-page: https://github.com/yexia553/k8sllm
Author: Your Name
Author-email: your.email@example.com
Classifier: Programming Language :: Python :: 3
Classifier: License :: OSI Approved :: MIT License
Classifier: Operating System :: OS Independent
Requires-Python: >=3.8
Requires-Dist: click>=8.0.0
Requires-Dist: pyyaml>=6.0.1
Requires-Dist: openai>=1.3.0
Requires-Dist: kubernetes>=28.1.0
Requires-Dist: python-dotenv>=1.0.0
